crossword_generator/__init__.py
crossword_generator/__main__.py
crossword_generator/common.py
crossword_generator/config.py
crossword_generator/layout_handler.py
crossword_generator/optimizer.py
crossword_generator/state.py
crossword_generator/tree_search.py
crossword_generator/word_handler.py
crossword_generator-0.2.2.dist-info/LICENSE.txt
crossword_generator-0.2.2.dist-info/METADATA
crossword_generator-0.2.2.dist-info/WHEEL
crossword_generator-0.2.2.dist-info/entry_points.txt
crossword_generator-0.2.2.dist-info/top_level.txt
crossword_generator-0.2.2.dist-info/RECORD
