Metadata-Version: 2.1
Name: crossword-generator
Version: 0.2.2
Summary: Generate crosswords using Monte Carlo Tree Search (MCTS)
Author-email: Jonas Schumacher <jonas.schumacher@tu-dortmund.de>
Project-URL: repository, https://github.com/jonas-schumacher/crossword-generator
Project-URL: blogpost, https://schumacher.pythonanywhere.com/udacity/crossword
Keywords: crossword,generator,creator,mcts,monte carlo tree search
Classifier: License :: OSI Approved :: MIT License
Classifier: Programming Language :: Python
Classifier: Programming Language :: Python :: 3
Requires-Python: >=3.8
License-File: LICENSE.txt
Requires-Dist: nltk>=3.5
Requires-Dist: pandas>=1.4.0
Requires-Dist: numpy>=1.22.0
Requires-Dist: tqdm>=4.41.0
Provides-Extra: build
Requires-Dist: build; extra == "build"
Requires-Dist: twine; extra == "build"
Provides-Extra: dev
Requires-Dist: black; extra == "dev"
Requires-Dist: pytest; extra == "dev"
